state_space_generator-0.1.9.dist-info/METADATA
state_space_generator-0.1.9.dist-info/top_level.txt
state_space_generator-0.1.9.dist-info/WHEEL
state_space_generator-0.1.9.dist-info/RECORD
state_space_generator-0.1.9.dist-info/LICENSE.md
state_space_generator/__init__.py
state_space_generator/state_space_generator.py
state_space_generator/scorpion/README.md
state_space_generator/scorpion/build_configs.py
state_space_generator/scorpion/build.py
state_space_generator/scorpion/fast-downward.py
state_space_generator/scorpion/LICENSE.md
state_space_generator/scorpion/src/CMakeLists.txt
state_space_generator/scorpion/src/cmake_modules/FindCplex.cmake
state_space_generator/scorpion/src/cmake_modules/FindClp.cmake
state_space_generator/scorpion/src/cmake_modules/FindOSI.cmake
state_space_generator/scorpion/src/cmake_modules/FindSoplex.cmake
state_space_generator/scorpion/src/cmake_modules/FastDownwardMacros.cmake
state_space_generator/scorpion/src/translate/timers.py
state_space_generator/scorpion/src/translate/sccs.py
state_space_generator/scorpion/src/translate/greedy_join.py
state_space_generator/scorpion/src/translate/axiom_rules.py
state_space_generator/scorpion/src/translate/simplify.py
state_space_generator/scorpion/src/translate/sas_tasks.py
state_space_generator/scorpion/src/translate/options.py
state_space_generator/scorpion/src/translate/pddl_to_prolog.py
state_space_generator/scorpion/src/translate/translate.py
state_space_generator/scorpion/src/translate/constraints.py
state_space_generator/scorpion/src/translate/graph.py
state_space_generator/scorpion/src/translate/split_rules.py
state_space_generator/scorpion/src/translate/build_model.py
state_space_generator/scorpion/src/translate/normalize.py
state_space_generator/scorpion/src/translate/fact_groups.py
state_space_generator/scorpion/src/translate/variable_order.py
state_space_generator/scorpion/src/translate/instantiate.py
state_space_generator/scorpion/src/translate/tools.py
state_space_generator/scorpion/src/translate/invariants.py
state_space_generator/scorpion/src/translate/invariant_finder.py
state_space_generator/scorpion/src/translate/tests/test_scripts.py
