Metadata-Version: 2.1
Name: state_space_generator
Version: 0.1.9
Summary: A tool for state space exploration of PDDL files
Home-page: https://github.com/drexlerd/state-space-generator
Author: Dominik Drexler, Jendrik Seipp
Author-email: dominik.drexler@liu.se, jendrik.seipp@liu.se
License: GNU
License-File: LICENSE.md
